{
  "key": "厦门大学(福建省厦门市,10384)",
  "code": "3501",
  "name": "厦门大学(福建省厦门市,10384)",
  "leaves": [],
  "groups2026": [
    {
      "groupCode": "第 003 组",
      "groupName": "第 003 组",
      "track": "历史",
      "selKe": "不限",
      "majors": [
        {
          "majorName": "人文科学试验班",
          "majorKey": "e70fa033",
          "selKe": "不限",
          "plan": 4,
          "tuition": "5460",
          "menlei": "他"
        },
        {
          "majorName": "经济学类",
          "majorKey": "0cabaa98",
          "selKe": "不限",
          "plan": 3,
          "tuition": "5460",
          "menlei": "经"
        },
        {
          "majorName": "外国语言文学类",
          "majorKey": "3c2f7b8b",
          "selKe": "不限",
          "plan": 2,
          "tuition": "5460",
          "menlei": "文"
        },
        {
          "majorName": "新闻传播学类",
          "majorKey": "331c4c8e",
          "selKe": "不限",
          "plan": 2,
          "tuition": "5460",
          "menlei": "文"
        },
        {
          "majorName": "会计学",
          "majorKey": "8aa56116",
          "selKe": "不限",
          "plan": 3,
          "tuition": "5460",
          "menlei": "管"
        }
      ]
    },
    {
      "groupCode": "第 004 组",
      "groupName": "第 004 组",
      "track": "历史",
      "selKe": "不限",
      "majors": [
        {
          "majorName": "英语",
          "majorKey": "49c5cdf9",
          "selKe": "不限",
          "plan": 1,
          "tuition": "待定",
          "menlei": "文"
        },
        {
          "majorName": "新闻学",
          "majorKey": "9c5f4a34",
          "selKe": "不限",
          "plan": 1,
          "tuition": "待定",
          "menlei": "文"
        }
      ]
    },
    {
      "groupCode": "第 005 组",
      "groupName": "第 005 组",
      "track": "历史",
      "selKe": "政治",
      "majors": [
        {
          "majorName": "公共管理类",
          "majorKey": "63da9816",
          "selKe": "政治",
          "plan": 3,
          "tuition": "5460",
          "menlei": "管"
        }
      ]
    },
    {
      "groupCode": "第 010 组",
      "groupName": "第 010 组",
      "track": "物理",
      "selKe": "不限",
      "majors": [
        {
          "majorName": "经济学类",
          "majorKey": "0cabaa98",
          "selKe": "不限",
          "plan": 7,
          "tuition": "5460",
          "menlei": "经"
        },
        {
          "majorName": "会计学",
          "majorKey": "8aa56116",
          "selKe": "不限",
          "plan": 2,
          "tuition": "5460",
          "menlei": "管"
        }
      ]
    },
    {
      "groupCode": "第 011 组",
      "groupName": "第 011 组",
      "track": "物理",
      "selKe": "不限",
      "majors": [
        {
          "majorName": "工商管理类",
          "majorKey": "b74128f4",
          "selKe": "不限",
          "plan": 1,
          "tuition": "5460",
          "menlei": "管"
        }
      ]
    },
    {
      "groupCode": "第 012 组",
      "groupName": "第 012 组",
      "track": "物理",
      "selKe": "化学",
      "majors": [
        {
          "majorName": "工科试验班",
          "majorKey": "b363aa3d",
          "selKe": "化学",
          "plan": 6,
          "tuition": "5460",
          "menlei": "他"
        },
        {
          "majorName": "工科试验班",
          "majorKey": "b363aa3d",
          "selKe": "化学",
          "plan": 3,
          "tuition": "5460",
          "menlei": "他"
        },
        {
          "majorName": "理科试验班",
          "majorKey": "54728189",
          "selKe": "化学",
          "plan": 4,
          "tuition": "5460",
          "menlei": "他"
        },
        {
          "majorName": "数学类",
          "majorKey": "33b3d741",
          "selKe": "化学",
          "plan": 2,
          "tuition": "5460",
          "menlei": "理"
        },
        {
          "majorName": "物理学类",
          "majorKey": "3d12abf2",
          "selKe": "化学",
          "plan": 4,
          "tuition": "5460",
          "menlei": "理"
        },
        {
          "majorName": "电子信息类",
          "majorKey": "5e0efed0",
          "selKe": "化学",
          "plan": 6,
          "tuition": "5460",
          "menlei": "工"
        },
        {
          "majorName": "计算机类",
          "majorKey": "8230723d",
          "selKe": "化学",
          "plan": 7,
          "tuition": "5460",
          "menlei": "工"
        }
      ]
    },
    {
      "groupCode": "第 013 组",
      "groupName": "第 013 组",
      "track": "物理",
      "selKe": "化学",
      "majors": [
        {
          "majorName": "物理学",
          "majorKey": "653f630d",
          "selKe": "化学",
          "plan": 1,
          "tuition": "待定",
          "menlei": "理"
        },
        {
          "majorName": "新能源科学与工程",
          "majorKey": "42b22d93",
          "selKe": "化学",
          "plan": 1,
          "tuition": "待定",
          "menlei": "工"
        },
        {
          "majorName": "电子信息工程",
          "majorKey": "fd603692",
          "selKe": "化学",
          "plan": 1,
          "tuition": "待定",
          "menlei": "工"
        },
        {
          "majorName": "人工智能",
          "majorKey": "2fec4169",
          "selKe": "化学",
          "plan": 1,
          "tuition": "待定",
          "menlei": "工"
        },
        {
          "majorName": "自动化",
          "majorKey": "da95770c",
          "selKe": "化学",
          "plan": 1,
          "tuition": "待定",
          "menlei": "工"
        },
        {
          "majorName": "计算机科学与技术",
          "majorKey": "1d486608",
          "selKe": "化学",
          "plan": 1,
          "tuition": "待定",
          "menlei": "工"
        },
        {
          "majorName": "数据科学与大数据技术",
          "majorKey": "bb0a25bd",
          "selKe": "化学",
          "plan": 2,
          "tuition": "待定",
          "menlei": "工"
        },
        {
          "majorName": "网络空间安全",
          "majorKey": "3093c484",
          "selKe": "化学",
          "plan": 1,
          "tuition": "待定",
          "menlei": "工"
        }
      ]
    }
  ]
}