{
  "key": "33b3d741",
  "name": "数学类",
  "schools": [
    {
      "sc": "1327",
      "sn": "山东大学",
      "mn": "数学类",
      "mk": "33b3d741",
      "minRank": 970,
      "minScore": 613,
      "year": 2025,
      "track": "理科"
    },
    {
      "sc": "1154",
      "sn": "吉林大学",
      "mn": "数学类",
      "mk": "33b3d741",
      "minRank": 1931,
      "minScore": 587,
      "year": 2025,
      "track": "理科"
    },
    {
      "sc": "1409",
      "sn": "中南大学",
      "mn": "数学类",
      "mk": "33b3d741",
      "minRank": 2035,
      "minScore": 585,
      "year": 2025,
      "track": "理科"
    },
    {
      "sc": "1543",
      "sn": "西安电子科技大学",
      "mn": "数学类",
      "mk": "33b3d741",
      "minRank": 2136,
      "minScore": 583,
      "year": 2025,
      "track": "理科"
    },
    {
      "sc": "1031",
      "sn": "中央财经大学",
      "mn": "数学类",
      "mk": "33b3d741",
      "minRank": 2179,
      "minScore": 582,
      "year": 2025,
      "track": "理科"
    },
    {
      "sc": "1008",
      "sn": "北京科技大学",
      "mn": "数学类",
      "mk": "33b3d741",
      "minRank": 2179,
      "minScore": 582,
      "year": 2025,
      "track": "理科"
    },
    {
      "sc": "1328",
      "sn": "中国海洋大学",
      "mn": "数学类",
      "mk": "33b3d741",
      "minRank": 3132,
      "minScore": 564,
      "year": 2025,
      "track": "理科"
    },
    {
      "sc": "5097",
      "sn": "武汉理工大学",
      "mn": "数学类",
      "mk": "33b3d741",
      "minRank": 3559,
      "minScore": 557,
      "year": 2025,
      "track": "理科"
    },
    {
      "sc": "1330",
      "sn": "中国石油大学（华东）",
      "mn": "数学类",
      "mk": "33b3d741",
      "minRank": 5648,
      "minScore": 529,
      "year": 2025,
      "track": "理科"
    },
    {
      "sc": "1053",
      "sn": "天津工业大学",
      "mn": "数学类",
      "mk": "33b3d741",
      "minRank": 7898,
      "minScore": 504,
      "year": 2025,
      "track": "理科"
    },
    {
      "sc": "1156",
      "sn": "长春理工大学",
      "mn": "数学类",
      "mk": "33b3d741",
      "minRank": 10150,
      "minScore": 483,
      "year": 2025,
      "track": "理科"
    },
    {
      "sc": "3654",
      "sn": "西交利物浦大学",
      "mn": "数学类",
      "mk": "33b3d741",
      "minRank": 16792,
      "minScore": 432,
      "year": 2025,
      "track": "理科"
    },
    {
      "sc": "1379",
      "sn": "河南财经政法大学",
      "mn": "数学类",
      "mk": "33b3d741",
      "minRank": 17313,
      "minScore": 428,
      "year": 2025,
      "track": "理科"
    }
  ]
}