{
  "code": "3995",
  "name": "青岛工学院",
  "leaves": [
    {
      "schoolCode": "3995",
      "majorKey": "2fec4169",
      "majorName": "人工智能",
      "selKe": "首选物理，再选化学",
      "years": [
        {
          "year": 2025,
          "track": "物理",
          "minScore": 453,
          "minRank": 80263,
          "maxScore": 0
        }
      ]
    },
    {
      "schoolCode": "3995",
      "majorKey": "e6801f33",
      "majorName": "信息安全",
      "selKe": "首选物理，再选化学",
      "years": [
        {
          "year": 2025,
          "track": "物理",
          "minScore": 451,
          "minRank": 81282,
          "maxScore": 0
        }
      ]
    },
    {
      "schoolCode": "3995",
      "majorKey": "28bd788f",
      "majorName": "制药工程",
      "selKe": "首选物理，再选化学",
      "years": [
        {
          "year": 2025,
          "track": "物理",
          "minScore": 440,
          "minRank": 86752,
          "maxScore": 0
        }
      ]
    },
    {
      "schoolCode": "3995",
      "majorKey": "9dde0fee",
      "majorName": "化学工程与工业生物工程",
      "selKe": "首选物理，再选化学",
      "years": [
        {
          "year": 2025,
          "track": "物理",
          "minScore": 447,
          "minRank": 83266,
          "maxScore": 0
        }
      ]
    },
    {
      "schoolCode": "3995",
      "majorKey": "320e7128",
      "majorName": "土木工程",
      "selKe": "首选物理，再选化学",
      "years": [
        {
          "year": 2025,
          "track": "物理",
          "minScore": 438,
          "minRank": 87686,
          "maxScore": 0
        }
      ]
    },
    {
      "schoolCode": "3995",
      "majorKey": "87f6e6a2",
      "majorName": "审计学",
      "selKe": "首选历史，再选不限",
      "years": [
        {
          "year": 2025,
          "track": "历史",
          "minScore": 471,
          "minRank": 20196,
          "maxScore": 0
        }
      ]
    },
    {
      "schoolCode": "3995",
      "majorKey": "07c28723",
      "majorName": "工商管理",
      "selKe": "首选历史，再选不限",
      "years": [
        {
          "year": 2025,
          "track": "历史",
          "minScore": 460,
          "minRank": 22299,
          "maxScore": 0
        },
        {
          "year": 2025,
          "track": "物理",
          "minScore": 447,
          "minRank": 83266,
          "maxScore": 0
        }
      ]
    },
    {
      "schoolCode": "3995",
      "majorKey": "59687759",
      "majorName": "应用心理学",
      "selKe": "首选历史，再选不限",
      "years": [
        {
          "year": 2025,
          "track": "历史",
          "minScore": 458,
          "minRank": 22672,
          "maxScore": 0
        }
      ]
    },
    {
      "schoolCode": "3995",
      "majorKey": "889e9381",
      "majorName": "数字媒体技术",
      "selKe": "首选物理，再选化学",
      "years": [
        {
          "year": 2025,
          "track": "物理",
          "minScore": 454,
          "minRank": 79793,
          "maxScore": 0
        }
      ]
    },
    {
      "schoolCode": "3995",
      "majorKey": "8f1def37",
      "majorName": "日语",
      "selKe": "首选历史，再选不限",
      "years": [
        {
          "year": 2025,
          "track": "历史",
          "minScore": 463,
          "minRank": 21728,
          "maxScore": 0
        }
      ]
    },
    {
      "schoolCode": "3995",
      "majorKey": "ed53a26b",
      "majorName": "智能制造工程",
      "selKe": "首选物理，再选化学",
      "years": [
        {
          "year": 2025,
          "track": "物理",
          "minScore": 447,
          "minRank": 83266,
          "maxScore": 0
        }
      ]
    },
    {
      "schoolCode": "3995",
      "majorKey": "2363aecb",
      "majorName": "智能建造",
      "selKe": "首选物理，再选化学",
      "years": [
        {
          "year": 2025,
          "track": "物理",
          "minScore": 430,
          "minRank": 91538,
          "maxScore": 0
        }
      ]
    },
    {
      "schoolCode": "3995",
      "majorKey": "55ff9da5",
      "majorName": "机械设计制造及其自动化",
      "selKe": "首选物理，再选化学",
      "years": [
        {
          "year": 2025,
          "track": "物理",
          "minScore": 457,
          "minRank": 78282,
          "maxScore": 0
        }
      ]
    },
    {
      "schoolCode": "3995",
      "majorKey": "fd603692",
      "majorName": "电子信息工程",
      "selKe": "首选物理，再选化学",
      "years": [
        {
          "year": 2025,
          "track": "物理",
          "minScore": 450,
          "minRank": 81785,
          "maxScore": 0
        }
      ]
    },
    {
      "schoolCode": "3995",
      "majorKey": "f3a3be38",
      "majorName": "知识产权",
      "selKe": "首选历史，再选不限",
      "years": [
        {
          "year": 2025,
          "track": "历史",
          "minScore": 467,
          "minRank": 20957,
          "maxScore": 0
        },
        {
          "year": 2025,
          "track": "物理",
          "minScore": 456,
          "minRank": 78788,
          "maxScore": 0
        }
      ]
    },
    {
      "schoolCode": "3995",
      "majorKey": "34997647",
      "majorName": "能源与动力工程",
      "selKe": "首选物理，再选化学",
      "years": [
        {
          "year": 2025,
          "track": "物理",
          "minScore": 453,
          "minRank": 80263,
          "maxScore": 0
        }
      ]
    },
    {
      "schoolCode": "3995",
      "majorKey": "da95770c",
      "majorName": "自动化",
      "selKe": "首选物理，再选化学",
      "years": [
        {
          "year": 2025,
          "track": "物理",
          "minScore": 456,
          "minRank": 78788,
          "maxScore": 0
        }
      ]
    },
    {
      "schoolCode": "3995",
      "majorKey": "49c5cdf9",
      "majorName": "英语",
      "selKe": "首选历史，再选不限",
      "years": [
        {
          "year": 2025,
          "track": "历史",
          "minScore": 462,
          "minRank": 21926,
          "maxScore": 0
        },
        {
          "year": 2025,
          "track": "物理",
          "minScore": 449,
          "minRank": 82283,
          "maxScore": 0
        }
      ]
    },
    {
      "schoolCode": "3995",
      "majorKey": "1d486608",
      "majorName": "计算机科学与技术",
      "selKe": "首选物理，再选化学",
      "years": [
        {
          "year": 2025,
          "track": "物理",
          "minScore": 455,
          "minRank": 79305,
          "maxScore": 0
        }
      ]
    },
    {
      "schoolCode": "3995",
      "majorKey": "0c33cbdd",
      "majorName": "软件工程",
      "selKe": "首选物理，再选化学",
      "years": [
        {
          "year": 2025,
          "track": "物理",
          "minScore": 457,
          "minRank": 78282,
          "maxScore": 0
        }
      ]
    },
    {
      "schoolCode": "3995",
      "majorKey": "7b7511cd",
      "majorName": "食品科学与工程",
      "selKe": "首选物理，再选化学",
      "years": [
        {
          "year": 2025,
          "track": "物理",
          "minScore": 447,
          "minRank": 83266,
          "maxScore": 0
        }
      ]
    }
  ],
  "plan2026": [
    {
      "majorName": "审计学",
      "majorKey": "87f6e6a2",
      "track": "历史",
      "selKe": "历史",
      "plan": 2,
      "tuition": "21000",
      "schooling": "4",
      "menlei": "管",
      "prevYear": 2025,
      "prevRank": 20196,
      "equivRank": 20196,
      "prevScore": 471
    },
    {
      "majorName": "知识产权",
      "majorKey": "f3a3be38",
      "track": "历史",
      "selKe": "历史",
      "plan": 2,
      "tuition": "22000",
      "schooling": "4",
      "menlei": "法",
      "prevYear": 2025,
      "prevRank": 20957,
      "equivRank": 20957,
      "prevScore": 467
    },
    {
      "majorName": "日语",
      "majorKey": "8f1def37",
      "track": "历史",
      "selKe": "历史",
      "plan": 2,
      "tuition": "21000",
      "schooling": "4",
      "menlei": "文",
      "prevYear": 2025,
      "prevRank": 21728,
      "equivRank": 21728,
      "prevScore": 463
    },
    {
      "majorName": "英语",
      "majorKey": "49c5cdf9",
      "track": "历史",
      "selKe": "历史",
      "plan": 2,
      "tuition": "21000",
      "schooling": "4",
      "menlei": "文",
      "prevYear": 2025,
      "prevRank": 21926,
      "equivRank": 21926,
      "prevScore": 462
    },
    {
      "majorName": "工商管理",
      "majorKey": "07c28723",
      "track": "历史",
      "selKe": "历史",
      "plan": 2,
      "tuition": "22000",
      "schooling": "4",
      "menlei": "管",
      "prevYear": 2025,
      "prevRank": 22299,
      "equivRank": 22299,
      "prevScore": 460
    },
    {
      "majorName": "应用心理学",
      "majorKey": "59687759",
      "track": "历史",
      "selKe": "历史",
      "plan": 2,
      "tuition": "23000",
      "schooling": "4",
      "menlei": "理",
      "prevYear": 2025,
      "prevRank": 22672,
      "equivRank": 22672,
      "prevScore": 458
    },
    {
      "majorName": "机械设计制造及其自动化",
      "majorKey": "55ff9da5",
      "track": "物理",
      "selKe": "物理,化学",
      "plan": 2,
      "tuition": "23000",
      "schooling": "4",
      "menlei": "工",
      "prevYear": 2025,
      "prevRank": 78282,
      "equivRank": 78282,
      "prevScore": 457
    },
    {
      "majorName": "软件工程",
      "majorKey": "0c33cbdd",
      "track": "物理",
      "selKe": "物理,化学",
      "plan": 2,
      "tuition": "23000",
      "schooling": "4",
      "menlei": "工",
      "prevYear": 2025,
      "prevRank": 78282,
      "equivRank": 78282,
      "prevScore": 457
    },
    {
      "majorName": "知识产权",
      "majorKey": "f3a3be38",
      "track": "物理",
      "selKe": "物理",
      "plan": 2,
      "tuition": "22000",
      "schooling": "4",
      "menlei": "法",
      "prevYear": 2025,
      "prevRank": 78788,
      "equivRank": 78788,
      "prevScore": 456
    },
    {
      "majorName": "自动化",
      "majorKey": "da95770c",
      "track": "物理",
      "selKe": "物理,化学",
      "plan": 2,
      "tuition": "23000",
      "schooling": "4",
      "menlei": "工",
      "prevYear": 2025,
      "prevRank": 78788,
      "equivRank": 78788,
      "prevScore": 456
    },
    {
      "majorName": "计算机科学与技术",
      "majorKey": "1d486608",
      "track": "物理",
      "selKe": "物理,化学",
      "plan": 2,
      "tuition": "25000",
      "schooling": "4",
      "menlei": "工",
      "prevYear": 2025,
      "prevRank": 79305,
      "equivRank": 79305,
      "prevScore": 455
    },
    {
      "majorName": "数字媒体技术",
      "majorKey": "889e9381",
      "track": "物理",
      "selKe": "物理,化学",
      "plan": 2,
      "tuition": "25000",
      "schooling": "4",
      "menlei": "工",
      "prevYear": 2025,
      "prevRank": 79793,
      "equivRank": 79793,
      "prevScore": 454
    },
    {
      "majorName": "人工智能",
      "majorKey": "2fec4169",
      "track": "物理",
      "selKe": "物理,化学",
      "plan": 2,
      "tuition": "25000",
      "schooling": "4",
      "menlei": "工",
      "prevYear": 2025,
      "prevRank": 80263,
      "equivRank": 80263,
      "prevScore": 453
    },
    {
      "majorName": "能源与动力工程",
      "majorKey": "34997647",
      "track": "物理",
      "selKe": "物理,化学",
      "plan": 2,
      "tuition": "25000",
      "schooling": "4",
      "menlei": "工",
      "prevYear": 2025,
      "prevRank": 80263,
      "equivRank": 80263,
      "prevScore": 453
    },
    {
      "majorName": "信息安全",
      "majorKey": "e6801f33",
      "track": "物理",
      "selKe": "物理,化学",
      "plan": 2,
      "tuition": "25000",
      "schooling": "4",
      "menlei": "工",
      "prevYear": 2025,
      "prevRank": 81282,
      "equivRank": 81282,
      "prevScore": 451
    },
    {
      "majorName": "电子信息工程",
      "majorKey": "fd603692",
      "track": "物理",
      "selKe": "物理,化学",
      "plan": 2,
      "tuition": "23000",
      "schooling": "4",
      "menlei": "工",
      "prevYear": 2025,
      "prevRank": 81785,
      "equivRank": 81785,
      "prevScore": 450
    },
    {
      "majorName": "英语",
      "majorKey": "49c5cdf9",
      "track": "物理",
      "selKe": "物理",
      "plan": 2,
      "tuition": "21000",
      "schooling": "4",
      "menlei": "文",
      "prevYear": 2025,
      "prevRank": 82283,
      "equivRank": 82283,
      "prevScore": 449
    },
    {
      "majorName": "化学工程与工业生物工程",
      "majorKey": "9dde0fee",
      "track": "物理",
      "selKe": "物理,化学",
      "plan": 3,
      "tuition": "23000",
      "schooling": "4",
      "menlei": "工",
      "prevYear": 2025,
      "prevRank": 83266,
      "equivRank": 83266,
      "prevScore": 447
    },
    {
      "majorName": "工商管理",
      "majorKey": "07c28723",
      "track": "物理",
      "selKe": "物理",
      "plan": 2,
      "tuition": "22000",
      "schooling": "4",
      "menlei": "管",
      "prevYear": 2025,
      "prevRank": 83266,
      "equivRank": 83266,
      "prevScore": 447
    },
    {
      "majorName": "智能制造工程",
      "majorKey": "ed53a26b",
      "track": "物理",
      "selKe": "物理,化学",
      "plan": 2,
      "tuition": "25000",
      "schooling": "4",
      "menlei": "工",
      "prevYear": 2025,
      "prevRank": 83266,
      "equivRank": 83266,
      "prevScore": 447
    },
    {
      "majorName": "食品科学与工程",
      "majorKey": "7b7511cd",
      "track": "物理",
      "selKe": "物理,化学",
      "plan": 3,
      "tuition": "25000",
      "schooling": "4",
      "menlei": "工",
      "prevYear": 2025,
      "prevRank": 83266,
      "equivRank": 83266,
      "prevScore": 447
    },
    {
      "majorName": "制药工程",
      "majorKey": "28bd788f",
      "track": "物理",
      "selKe": "物理,化学",
      "plan": 2,
      "tuition": "23000",
      "schooling": "4",
      "menlei": "工",
      "prevYear": 2025,
      "prevRank": 86752,
      "equivRank": 86752,
      "prevScore": 440
    },
    {
      "majorName": "土木工程",
      "majorKey": "320e7128",
      "track": "物理",
      "selKe": "物理,化学",
      "plan": 2,
      "tuition": "23000",
      "schooling": "4",
      "menlei": "工",
      "prevYear": 2025,
      "prevRank": 87686,
      "equivRank": 87686,
      "prevScore": 438
    },
    {
      "majorName": "智能建造",
      "majorKey": "2363aecb",
      "track": "物理",
      "selKe": "物理,化学",
      "plan": 2,
      "tuition": "23000",
      "schooling": "4",
      "menlei": "工",
      "prevYear": 2025,
      "prevRank": 91538,
      "equivRank": 91538,
      "prevScore": 430
    }
  ]
}