{
  "key": "重庆医科大学",
  "code": "5031",
  "name": "重庆医科大学",
  "leaves": [
    {
      "schoolKey": "重庆医科大学",
      "schoolCode": "5031",
      "majorKey": "618f7040",
      "majorName": "临床医学",
      "selKe": "物理、化学(2科必选)",
      "years": [
        {
          "year": 2022,
          "track": "综合",
          "minScore": 652,
          "minRank": 7522,
          "maxScore": 0
        },
        {
          "year": 2023,
          "track": "综合",
          "minScore": 660,
          "minRank": 7878,
          "maxScore": 0
        },
        {
          "year": 2024,
          "track": "综合",
          "minScore": 664,
          "minRank": 6652,
          "maxScore": 0
        },
        {
          "year": 2025,
          "track": "综合",
          "minScore": 652,
          "minRank": 10086,
          "maxScore": 0
        }
      ]
    },
    {
      "schoolKey": "重庆医科大学",
      "schoolCode": "5031",
      "majorKey": "c69b91ea",
      "majorName": "临床药学",
      "selKe": "物理、化学(2科必选)",
      "years": [
        {
          "year": 2022,
          "track": "综合",
          "minScore": 631,
          "minRank": 19595,
          "maxScore": 0
        },
        {
          "year": 2023,
          "track": "综合",
          "minScore": 637,
          "minRank": 20243,
          "maxScore": 0
        },
        {
          "year": 2024,
          "track": "综合",
          "minScore": 625,
          "minRank": 29009,
          "maxScore": 0
        },
        {
          "year": 2025,
          "track": "综合",
          "minScore": 603,
          "minRank": 48179,
          "maxScore": 0
        }
      ]
    },
    {
      "schoolKey": "重庆医科大学",
      "schoolCode": "5031",
      "majorKey": "db9ffa2a",
      "majorName": "儿科学",
      "selKe": "物理、化学(2科必选)",
      "years": [
        {
          "year": 2022,
          "track": "综合",
          "minScore": 635,
          "minRank": 16803,
          "maxScore": 0
        },
        {
          "year": 2023,
          "track": "综合",
          "minScore": 640,
          "minRank": 18780,
          "maxScore": 0
        },
        {
          "year": 2024,
          "track": "综合",
          "minScore": 632,
          "minRank": 23535,
          "maxScore": 0
        },
        {
          "year": 2025,
          "track": "综合",
          "minScore": 617,
          "minRank": 34108,
          "maxScore": 0
        }
      ]
    },
    {
      "schoolKey": "重庆医科大学",
      "schoolCode": "5031",
      "majorKey": "30e8a552",
      "majorName": "公共事业管理",
      "selKe": "不限",
      "years": [
        {
          "year": 2022,
          "track": "综合",
          "minScore": 602,
          "minRank": 46298,
          "maxScore": 0
        },
        {
          "year": 2023,
          "track": "综合",
          "minScore": 600,
          "minRank": 52618,
          "maxScore": 0
        },
        {
          "year": 2024,
          "track": "综合",
          "minScore": 610,
          "minRank": 43479,
          "maxScore": 0
        },
        {
          "year": 2025,
          "track": "综合",
          "minScore": 602,
          "minRank": 49869,
          "maxScore": 0
        }
      ]
    },
    {
      "schoolKey": "重庆医科大学",
      "schoolCode": "5031",
      "majorKey": "58e43044",
      "majorName": "医学信息工程",
      "selKe": "物理、化学(2科必选)",
      "years": [
        {
          "year": 2023,
          "track": "综合",
          "minScore": 617,
          "minRank": 36095,
          "maxScore": 0
        },
        {
          "year": 2024,
          "track": "综合",
          "minScore": 605,
          "minRank": 47636,
          "maxScore": 0
        },
        {
          "year": 2025,
          "track": "综合",
          "minScore": 601,
          "minRank": 50439,
          "maxScore": 0
        }
      ]
    },
    {
      "schoolKey": "重庆医科大学",
      "schoolCode": "5031",
      "majorKey": "9b0a4bb0",
      "majorName": "医学实验技术",
      "selKe": "物/化/生(3选1)",
      "years": [
        {
          "year": 2022,
          "track": "综合",
          "minScore": 619,
          "minRank": 29496,
          "maxScore": 0
        }
      ]
    },
    {
      "schoolKey": "重庆医科大学",
      "schoolCode": "5031",
      "majorKey": "5780af73",
      "majorName": "医学影像学",
      "selKe": "物理、化学(2科必选)",
      "years": [
        {
          "year": 2022,
          "track": "综合",
          "minScore": 635,
          "minRank": 16803,
          "maxScore": 0
        },
        {
          "year": 2023,
          "track": "综合",
          "minScore": 642,
          "minRank": 17295,
          "maxScore": 0
        },
        {
          "year": 2024,
          "track": "综合",
          "minScore": 638,
          "minRank": 19494,
          "maxScore": 0
        },
        {
          "year": 2025,
          "track": "综合",
          "minScore": 626,
          "minRank": 26249,
          "maxScore": 0
        }
      ]
    },
    {
      "schoolKey": "重庆医科大学",
      "schoolCode": "5031",
      "majorKey": "11fef64a",
      "majorName": "医学影像技术",
      "selKe": "物理、化学(2科必选)",
      "years": [
        {
          "year": 2022,
          "track": "综合",
          "minScore": 612,
          "minRank": 35884,
          "maxScore": 0
        },
        {
          "year": 2023,
          "track": "综合",
          "minScore": 621,
          "minRank": 32585,
          "maxScore": 0
        },
        {
          "year": 2024,
          "track": "综合",
          "minScore": 593,
          "minRank": 61128,
          "maxScore": 0
        },
        {
          "year": 2025,
          "track": "综合",
          "minScore": 591,
          "minRank": 62347,
          "maxScore": 0
        }
      ]
    },
    {
      "schoolKey": "重庆医科大学",
      "schoolCode": "5031",
      "majorKey": "f106fa76",
      "majorName": "医学检验技术",
      "selKe": "物理、化学(2科必选)",
      "years": [
        {
          "year": 2022,
          "track": "综合",
          "minScore": 614,
          "minRank": 33965,
          "maxScore": 0
        },
        {
          "year": 2023,
          "track": "综合",
          "minScore": 621,
          "minRank": 33037,
          "maxScore": 0
        },
        {
          "year": 2024,
          "track": "综合",
          "minScore": 602,
          "minRank": 51198,
          "maxScore": 0
        },
        {
          "year": 2025,
          "track": "综合",
          "minScore": 596,
          "minRank": 55934,
          "maxScore": 0
        }
      ]
    },
    {
      "schoolKey": "重庆医科大学",
      "schoolCode": "5031",
      "majorKey": "2c72d9e9",
      "majorName": "卫生检验与检疫",
      "selKe": "物理、化学(2科必选)",
      "years": [
        {
          "year": 2022,
          "track": "综合",
          "minScore": 607,
          "minRank": 41009,
          "maxScore": 0
        },
        {
          "year": 2023,
          "track": "综合",
          "minScore": 610,
          "minRank": 42680,
          "maxScore": 0
        },
        {
          "year": 2024,
          "track": "综合",
          "minScore": 550,
          "minRank": 110955,
          "maxScore": 0
        },
        {
          "year": 2025,
          "track": "综合",
          "minScore": 556,
          "minRank": 104487,
          "maxScore": 0
        }
      ]
    },
    {
      "schoolKey": "重庆医科大学",
      "schoolCode": "5031",
      "majorKey": "c162bced",
      "majorName": "口腔医学",
      "selKe": "物理、化学(2科必选)",
      "years": [
        {
          "year": 2022,
          "track": "综合",
          "minScore": 651,
          "minRank": 7960,
          "maxScore": 0
        },
        {
          "year": 2023,
          "track": "综合",
          "minScore": 659,
          "minRank": 8347,
          "maxScore": 0
        },
        {
          "year": 2024,
          "track": "综合",
          "minScore": 658,
          "minRank": 8972,
          "maxScore": 0
        },
        {
          "year": 2025,
          "track": "综合",
          "minScore": 647,
          "minRank": 12755,
          "maxScore": 0
        }
      ]
    },
    {
      "schoolKey": "重庆医科大学",
      "schoolCode": "5031",
      "majorKey": "e849f952",
      "majorName": "口腔医学技术",
      "selKe": "物理、化学(2科必选)",
      "years": [
        {
          "year": 2022,
          "track": "综合",
          "minScore": 625,
          "minRank": 24317,
          "maxScore": 0
        },
        {
          "year": 2023,
          "track": "综合",
          "minScore": 633,
          "minRank": 23089,
          "maxScore": 0
        },
        {
          "year": 2024,
          "track": "综合",
          "minScore": 605,
          "minRank": 47754,
          "maxScore": 0
        },
        {
          "year": 2025,
          "track": "综合",
          "minScore": 593,
          "minRank": 59511,
          "maxScore": 0
        }
      ]
    },
    {
      "schoolKey": "重庆医科大学",
      "schoolCode": "5031",
      "majorKey": "10433b46",
      "majorName": "听力与言语康复学",
      "selKe": "物理、化学(2科必选)",
      "years": [
        {
          "year": 2023,
          "track": "综合",
          "minScore": 602,
          "minRank": 50449,
          "maxScore": 0
        },
        {
          "year": 2024,
          "track": "综合",
          "minScore": 566,
          "minRank": 91662,
          "maxScore": 0
        },
        {
          "year": 2025,
          "track": "综合",
          "minScore": 569,
          "minRank": 88590,
          "maxScore": 0
        }
      ]
    },
    {
      "schoolKey": "重庆医科大学",
      "schoolCode": "5031",
      "majorKey": "8ca67fa5",
      "majorName": "基础医学",
      "selKe": "物理、化学(2科必选)",
      "years": [
        {
          "year": 2022,
          "track": "综合",
          "minScore": 624,
          "minRank": 25138,
          "maxScore": 0
        },
        {
          "year": 2023,
          "track": "综合",
          "minScore": 631,
          "minRank": 24858,
          "maxScore": 0
        },
        {
          "year": 2024,
          "track": "综合",
          "minScore": 569,
          "minRank": 88466,
          "maxScore": 0
        },
        {
          "year": 2025,
          "track": "综合",
          "minScore": 589,
          "minRank": 64135,
          "maxScore": 0
        }
      ]
    },
    {
      "schoolKey": "重庆医科大学",
      "schoolCode": "5031",
      "majorKey": "d054f8d1",
      "majorName": "应用统计学",
      "selKe": "物理、化学(2科必选)",
      "years": [
        {
          "year": 2022,
          "track": "综合",
          "minScore": 604,
          "minRank": 44129,
          "maxScore": 0
        },
        {
          "year": 2023,
          "track": "综合",
          "minScore": 610,
          "minRank": 42789,
          "maxScore": 0
        },
        {
          "year": 2024,
          "track": "综合",
          "minScore": 601,
          "minRank": 52076,
          "maxScore": 0
        },
        {
          "year": 2025,
          "track": "综合",
          "minScore": 590,
          "minRank": 63072,
          "maxScore": 0
        }
      ]
    },
    {
      "schoolKey": "重庆医科大学",
      "schoolCode": "5031",
      "majorKey": "a507c400",
      "majorName": "康复治疗学",
      "selKe": "物理、化学(2科必选)",
      "years": [
        {
          "year": 2022,
          "track": "综合",
          "minScore": 609,
          "minRank": 38923,
          "maxScore": 0
        },
        {
          "year": 2025,
          "track": "综合",
          "minScore": 562,
          "minRank": 97710,
          "maxScore": 0
        }
      ]
    },
    {
      "schoolKey": "重庆医科大学",
      "schoolCode": "5031",
      "majorKey": "c7acab0a",
      "majorName": "护理学",
      "selKe": "化学必选",
      "years": [
        {
          "year": 2022,
          "track": "综合",
          "minScore": 602,
          "minRank": 46298,
          "maxScore": 0
        },
        {
          "year": 2023,
          "track": "综合",
          "minScore": 611,
          "minRank": 41777,
          "maxScore": 0
        },
        {
          "year": 2024,
          "track": "综合",
          "minScore": 597,
          "minRank": 57192,
          "maxScore": 0
        },
        {
          "year": 2025,
          "track": "综合",
          "minScore": 577,
          "minRank": 78645,
          "maxScore": 0
        }
      ]
    },
    {
      "schoolKey": "重庆医科大学",
      "schoolCode": "5031",
      "majorKey": "11a5a631",
      "majorName": "智能医学工程",
      "selKe": "物理、化学(2科必选)",
      "years": [
        {
          "year": 2023,
          "track": "综合",
          "minScore": 614,
          "minRank": 39214,
          "maxScore": 0
        },
        {
          "year": 2024,
          "track": "综合",
          "minScore": 611,
          "minRank": 41771,
          "maxScore": 0
        },
        {
          "year": 2025,
          "track": "综合",
          "minScore": 606,
          "minRank": 45173,
          "maxScore": 0
        }
      ]
    },
    {
      "schoolKey": "重庆医科大学",
      "schoolCode": "5031",
      "majorKey": "0798db5f",
      "majorName": "法医学",
      "selKe": "物理、化学(2科必选)",
      "years": [
        {
          "year": 2022,
          "track": "综合",
          "minScore": 623,
          "minRank": 25936,
          "maxScore": 0
        },
        {
          "year": 2023,
          "track": "综合",
          "minScore": 636,
          "minRank": 21286,
          "maxScore": 0
        },
        {
          "year": 2024,
          "track": "综合",
          "minScore": 624,
          "minRank": 29923,
          "maxScore": 0
        },
        {
          "year": 2025,
          "track": "综合",
          "minScore": 616,
          "minRank": 35654,
          "maxScore": 0
        }
      ]
    },
    {
      "schoolKey": "重庆医科大学",
      "schoolCode": "5031",
      "majorKey": "da8a20f0",
      "majorName": "生物信息学",
      "selKe": "物理、化学(2科必选)",
      "years": [
        {
          "year": 2022,
          "track": "综合",
          "minScore": 615,
          "minRank": 33061,
          "maxScore": 0
        },
        {
          "year": 2023,
          "track": "综合",
          "minScore": 625,
          "minRank": 29630,
          "maxScore": 0
        },
        {
          "year": 2024,
          "track": "综合",
          "minScore": 603,
          "minRank": 50266,
          "maxScore": 0
        },
        {
          "year": 2025,
          "track": "综合",
          "minScore": 602,
          "minRank": 50090,
          "maxScore": 0
        }
      ]
    },
    {
      "schoolKey": "重庆医科大学",
      "schoolCode": "5031",
      "majorKey": "27c81131",
      "majorName": "生物医学工程",
      "selKe": "物理、化学(2科必选)",
      "years": [
        {
          "year": 2022,
          "track": "综合",
          "minScore": 613,
          "minRank": 34902,
          "maxScore": 0
        },
        {
          "year": 2023,
          "track": "综合",
          "minScore": 629,
          "minRank": 26357,
          "maxScore": 0
        },
        {
          "year": 2024,
          "track": "综合",
          "minScore": 622,
          "minRank": 31783,
          "maxScore": 0
        },
        {
          "year": 2025,
          "track": "综合",
          "minScore": 613,
          "minRank": 38032,
          "maxScore": 0
        }
      ]
    },
    {
      "schoolKey": "重庆医科大学",
      "schoolCode": "5031",
      "majorKey": "e86ddf0a",
      "majorName": "精神医学",
      "selKe": "物理、化学(2科必选)",
      "years": [
        {
          "year": 2022,
          "track": "综合",
          "minScore": 623,
          "minRank": 25936,
          "maxScore": 0
        },
        {
          "year": 2023,
          "track": "综合",
          "minScore": 630,
          "minRank": 25391,
          "maxScore": 0
        },
        {
          "year": 2024,
          "track": "综合",
          "minScore": 633,
          "minRank": 22942,
          "maxScore": 0
        },
        {
          "year": 2025,
          "track": "综合",
          "minScore": 595,
          "minRank": 57475,
          "maxScore": 0
        }
      ]
    },
    {
      "schoolKey": "重庆医科大学",
      "schoolCode": "5031",
      "majorKey": "49c5cdf9",
      "majorName": "英语",
      "selKe": "不限",
      "years": [
        {
          "year": 2022,
          "track": "综合",
          "minScore": 603,
          "minRank": 45195,
          "maxScore": 0
        },
        {
          "year": 2023,
          "track": "综合",
          "minScore": 618,
          "minRank": 35457,
          "maxScore": 0
        },
        {
          "year": 2024,
          "track": "综合",
          "minScore": 615,
          "minRank": 38560,
          "maxScore": 0
        }
      ]
    },
    {
      "schoolKey": "重庆医科大学",
      "schoolCode": "5031",
      "majorKey": "dc8e7679",
      "majorName": "药物制剂",
      "selKe": "化学必选",
      "years": [
        {
          "year": 2022,
          "track": "综合",
          "minScore": 606,
          "minRank": 42068,
          "maxScore": 0
        },
        {
          "year": 2023,
          "track": "综合",
          "minScore": 610,
          "minRank": 42659,
          "maxScore": 0
        }
      ]
    },
    {
      "schoolKey": "重庆医科大学",
      "schoolCode": "5031",
      "majorKey": "1954d9c9",
      "majorName": "预防医学",
      "selKe": "物理、化学(2科必选)",
      "years": [
        {
          "year": 2022,
          "track": "综合",
          "minScore": 625,
          "minRank": 24317,
          "maxScore": 0
        },
        {
          "year": 2023,
          "track": "综合",
          "minScore": 632,
          "minRank": 24286,
          "maxScore": 0
        },
        {
          "year": 2024,
          "track": "综合",
          "minScore": 611,
          "minRank": 41740,
          "maxScore": 0
        },
        {
          "year": 2025,
          "track": "综合",
          "minScore": 601,
          "minRank": 50462,
          "maxScore": 0
        }
      ]
    },
    {
      "schoolKey": "重庆医科大学",
      "schoolCode": "5031",
      "majorKey": "49f6ae18",
      "majorName": "食品卫生与营养学",
      "selKe": "物/化/生(3选1)",
      "years": [
        {
          "year": 2022,
          "track": "综合",
          "minScore": 613,
          "minRank": 34902,
          "maxScore": 0
        },
        {
          "year": 2023,
          "track": "综合",
          "minScore": 619,
          "minRank": 34637,
          "maxScore": 0
        }
      ]
    },
    {
      "schoolKey": "重庆医科大学",
      "schoolCode": "5031",
      "majorKey": "83eea431",
      "majorName": "麻醉学",
      "selKe": "物理、化学(2科必选)",
      "years": [
        {
          "year": 2022,
          "track": "综合",
          "minScore": 633,
          "minRank": 18156,
          "maxScore": 0
        },
        {
          "year": 2023,
          "track": "综合",
          "minScore": 639,
          "minRank": 18918,
          "maxScore": 0
        },
        {
          "year": 2024,
          "track": "综合",
          "minScore": 633,
          "minRank": 23002,
          "maxScore": 0
        },
        {
          "year": 2025,
          "track": "综合",
          "minScore": 622,
          "minRank": 29539,
          "maxScore": 0
        }
      ]
    }
  ],
  "plan2026": [
    {
      "majorName": "临床医学",
      "majorKey": "618f7040",
      "track": "综合",
      "selKe": "物理、化学(2科必选)",
      "plan": 14,
      "tuition": "6250",
      "schooling": "五年",
      "menlei": "医",
      "prevYear": 2025,
      "prevRank": 10086,
      "equivRank": 10086,
      "prevScore": 652
    },
    {
      "majorName": "口腔医学",
      "majorKey": "c162bced",
      "track": "综合",
      "selKe": "物理、化学(2科必选)",
      "plan": 2,
      "tuition": "6250",
      "schooling": "五年",
      "menlei": "医",
      "prevYear": 2025,
      "prevRank": 12755,
      "equivRank": 12755,
      "prevScore": 647
    },
    {
      "majorName": "医学影像学",
      "majorKey": "5780af73",
      "track": "综合",
      "selKe": "物理、化学(2科必选)",
      "plan": 2,
      "tuition": "6250",
      "schooling": "五年",
      "menlei": "医",
      "prevYear": 2025,
      "prevRank": 26249,
      "equivRank": 26249,
      "prevScore": 626
    },
    {
      "majorName": "麻醉学",
      "majorKey": "83eea431",
      "track": "综合",
      "selKe": "物理、化学(2科必选)",
      "plan": 2,
      "tuition": "6250",
      "schooling": "五年",
      "menlei": "医",
      "prevYear": 2025,
      "prevRank": 29539,
      "equivRank": 29539,
      "prevScore": 622
    },
    {
      "majorName": "儿科学",
      "majorKey": "db9ffa2a",
      "track": "综合",
      "selKe": "物理、化学(2科必选)",
      "plan": 3,
      "tuition": "6250",
      "schooling": "五年",
      "menlei": "医",
      "prevYear": 2025,
      "prevRank": 34108,
      "equivRank": 34108,
      "prevScore": 617
    },
    {
      "majorName": "法医学",
      "majorKey": "0798db5f",
      "track": "综合",
      "selKe": "物理、化学(2科必选)",
      "plan": 2,
      "tuition": "6250",
      "schooling": "五年",
      "menlei": "医",
      "prevYear": 2025,
      "prevRank": 35654,
      "equivRank": 35654,
      "prevScore": 616
    },
    {
      "majorName": "生物医学工程",
      "majorKey": "27c81131",
      "track": "综合",
      "selKe": "物理、化学(2科必选)",
      "plan": 2,
      "tuition": "4625",
      "schooling": "五年",
      "menlei": "工",
      "prevYear": 2025,
      "prevRank": 38032,
      "equivRank": 38032,
      "prevScore": 613
    },
    {
      "majorName": "智能医学工程",
      "majorKey": "11a5a631",
      "track": "综合",
      "selKe": "物理、化学(2科必选)",
      "plan": 1,
      "tuition": "6250",
      "schooling": "四年",
      "menlei": "医",
      "prevYear": 2025,
      "prevRank": 45173,
      "equivRank": 45173,
      "prevScore": 606
    },
    {
      "majorName": "临床药学",
      "majorKey": "c69b91ea",
      "track": "综合",
      "selKe": "物理、化学(2科必选)",
      "plan": 2,
      "tuition": "6250",
      "schooling": "五年",
      "menlei": "医",
      "prevYear": 2025,
      "prevRank": 48179,
      "equivRank": 48179,
      "prevScore": 603
    },
    {
      "majorName": "公共事业管理",
      "majorKey": "30e8a552",
      "track": "综合",
      "selKe": "不限",
      "plan": 1,
      "tuition": "4625",
      "schooling": "四年",
      "menlei": "管",
      "prevYear": 2025,
      "prevRank": 49869,
      "equivRank": 49869,
      "prevScore": 602
    },
    {
      "majorName": "生物信息学",
      "majorKey": "da8a20f0",
      "track": "综合",
      "selKe": "物理、化学(2科必选)",
      "plan": 1,
      "tuition": "4625",
      "schooling": "四年",
      "menlei": "理",
      "prevYear": 2025,
      "prevRank": 50090,
      "equivRank": 50090,
      "prevScore": 602
    },
    {
      "majorName": "医学信息工程",
      "majorKey": "58e43044",
      "track": "综合",
      "selKe": "物理、化学(2科必选)",
      "plan": 1,
      "tuition": "4625",
      "schooling": "四年",
      "menlei": "工",
      "prevYear": 2025,
      "prevRank": 50439,
      "equivRank": 50439,
      "prevScore": 601
    },
    {
      "majorName": "预防医学",
      "majorKey": "1954d9c9",
      "track": "综合",
      "selKe": "物理、化学(2科必选)",
      "plan": 2,
      "tuition": "6250",
      "schooling": "五年",
      "menlei": "医",
      "prevYear": 2025,
      "prevRank": 50462,
      "equivRank": 50462,
      "prevScore": 601
    },
    {
      "majorName": "医学检验技术",
      "majorKey": "f106fa76",
      "track": "综合",
      "selKe": "物理、化学(2科必选)",
      "plan": 3,
      "tuition": "6250",
      "schooling": "四年",
      "menlei": "医",
      "prevYear": 2025,
      "prevRank": 55934,
      "equivRank": 55934,
      "prevScore": 596
    },
    {
      "majorName": "精神医学",
      "majorKey": "e86ddf0a",
      "track": "综合",
      "selKe": "物理、化学(2科必选)",
      "plan": 3,
      "tuition": "62000",
      "schooling": "五年",
      "menlei": "医",
      "coop": true,
      "prevYear": 2025,
      "prevRank": 57475,
      "equivRank": 57475,
      "prevScore": 595
    },
    {
      "majorName": "口腔医学技术",
      "majorKey": "e849f952",
      "track": "综合",
      "selKe": "物理、化学(2科必选)",
      "plan": 2,
      "tuition": "6250",
      "schooling": "四年",
      "menlei": "医",
      "prevYear": 2025,
      "prevRank": 59511,
      "equivRank": 59511,
      "prevScore": 593
    },
    {
      "majorName": "医学影像技术",
      "majorKey": "11fef64a",
      "track": "综合",
      "selKe": "物理、化学(2科必选)",
      "plan": 2,
      "tuition": "6250",
      "schooling": "四年",
      "menlei": "医",
      "prevYear": 2025,
      "prevRank": 62347,
      "equivRank": 62347,
      "prevScore": 591
    },
    {
      "majorName": "应用统计学",
      "majorKey": "d054f8d1",
      "track": "综合",
      "selKe": "物理、化学(2科必选)",
      "plan": 2,
      "tuition": "4625",
      "schooling": "四年",
      "menlei": "理",
      "prevYear": 2025,
      "prevRank": 63072,
      "equivRank": 63072,
      "prevScore": 590
    },
    {
      "majorName": "基础医学",
      "majorKey": "8ca67fa5",
      "track": "综合",
      "selKe": "物理、化学(2科必选)",
      "plan": 1,
      "tuition": "6250",
      "schooling": "五年",
      "menlei": "医",
      "prevYear": 2025,
      "prevRank": 64135,
      "equivRank": 64135,
      "prevScore": 589
    },
    {
      "majorName": "护理学",
      "majorKey": "c7acab0a",
      "track": "综合",
      "selKe": "化学必选",
      "plan": 4,
      "tuition": "6250",
      "schooling": "四年",
      "menlei": "医",
      "prevYear": 2025,
      "prevRank": 78645,
      "equivRank": 78645,
      "prevScore": 577
    },
    {
      "majorName": "听力与言语康复学",
      "majorKey": "10433b46",
      "track": "综合",
      "selKe": "物理、化学(2科必选)",
      "plan": 1,
      "tuition": "6250",
      "schooling": "四年",
      "menlei": "医",
      "prevYear": 2025,
      "prevRank": 88590,
      "equivRank": 88590,
      "prevScore": 569
    },
    {
      "majorName": "康复治疗学",
      "majorKey": "a507c400",
      "track": "综合",
      "selKe": "物理、化学(2科必选)",
      "plan": 2,
      "tuition": "62000",
      "schooling": "四年",
      "menlei": "医",
      "coop": true,
      "prevYear": 2025,
      "prevRank": 97710,
      "equivRank": 97710,
      "prevScore": 562
    },
    {
      "majorName": "卫生检验与检疫",
      "majorKey": "2c72d9e9",
      "track": "综合",
      "selKe": "物理、化学(2科必选)",
      "plan": 1,
      "tuition": "6250",
      "schooling": "四年",
      "menlei": "医",
      "prevYear": 2025,
      "prevRank": 104487,
      "equivRank": 104487,
      "prevScore": 556
    }
  ]
}