{
  "key": "c98687d6",
  "name": "现代移动通信技术",
  "schools": [
    {
      "sc": "3223",
      "sn": "江苏海事职业技术学院",
      "mk": "c98687d6",
      "minRank": 182518,
      "year": 2022,
      "track": "综合"
    },
    {
      "sc": "0128",
      "sn": "浙江邮电职业技术学院",
      "mk": "c98687d6",
      "minRank": 184372,
      "year": 2025,
      "track": "综合"
    },
    {
      "sc": "4527",
      "sn": "桂林师范学院",
      "mk": "c98687d6",
      "minRank": 217387,
      "year": 2025,
      "track": "综合"
    },
    {
      "sc": "3621",
      "sn": "江西科技学院",
      "mk": "c98687d6",
      "minRank": 231701,
      "year": 2022,
      "track": "综合"
    },
    {
      "sc": "3234",
      "sn": "金肯职业技术学院",
      "mk": "c98687d6",
      "minRank": 262600,
      "year": 2023,
      "track": "综合"
    },
    {
      "sc": "3769",
      "sn": "山东工程职业技术大学",
      "mk": "c98687d6",
      "minRank": 271702,
      "year": 2024,
      "track": "综合"
    },
    {
      "sc": "5181",
      "sn": "南充科技职业学院",
      "mk": "c98687d6",
      "minRank": 280087,
      "year": 2025,
      "track": "综合"
    },
    {
      "sc": "4601",
      "sn": "海口经济学院",
      "mk": "c98687d6",
      "minRank": 283394,
      "year": 2025,
      "track": "综合"
    },
    {
      "sc": "5039",
      "sn": "重庆电讯职业学院",
      "mk": "c98687d6",
      "minRank": 283553,
      "year": 2025,
      "track": "综合"
    },
    {
      "sc": "4399",
      "sn": "潇湘职业学院",
      "mk": "c98687d6",
      "minRank": 290790,
      "year": 2025,
      "track": "综合"
    },
    {
      "sc": "5044",
      "sn": "重庆科技职业学院",
      "mk": "c98687d6",
      "minRank": 290790,
      "year": 2025,
      "track": "综合"
    },
    {
      "sc": "5176",
      "sn": "四川电子机械职业技术学院",
      "mk": "c98687d6",
      "minRank": 290790,
      "year": 2025,
      "track": "综合"
    }
  ]
}